{
  "project_info": {
    "project_number": "558718791256",
    "project_id": "abdelaleem-f520a",
    "storage_bucket": "abdelaleem-f520a.appspot.com"
  },
  "client": [
    {
      "client_info": {
        "mobilesdk_app_id": "1:558718791256:android:568a4ae2ccbe7731d7a42d",
        "android_client_info": {
          "package_name": "com.example.e_commerce"
        }
      },
      "oauth_client": [
        {
          "client_id": "558718791256-v4fa066q8oimcf8ns6si6dto58r4vbli.apps.googleusercontent.com",
          "client_type": 3
        }
      ],
      "api_key": [
        {
          "current_key": "AIzaSyCOm6L9xT3-wddvyDLWMTl4E8UenUPVzmE"
        }
      ],
      "services": {
        "appinvite_service": {
          "other_platform_oauth_client": [
            {
              "client_id": "558718791256-v4fa066q8oimcf8ns6si6dto58r4vbli.apps.googleusercontent.com",
              "client_type": 3
            }
          ]
        }
      }
    }
  ],
  "configuration_version": "1"
}